{
  "generationParameters": {
    "generationDate": "Fri Oct 10 2025 09:49:42 GMT+0000 (Coordinated Universal Time)",
    "generatorPlatform": "SAP Business Application Studio",
    "serviceType": "SAP System (ABAP On-Premise)",
    "metadataFilename": "",
    "serviceUrl": "https://services.odata.org/V2/(S(firqkuzfb4agxs2jowc4en1z))/OData/OData.svc/",
    "appName": "manageproduct",
    "appTitle": "Manage Product",
    "appDescription": "An SAP Fiori application.",
    "appNamespace": "",
    "ui5Theme": "sap_horizon",
    "ui5Version": "1.141.1",
    "enableCodeAssist": false,
    "enableEslint": false,
    "enableTypeScript": false,
    "showMockDataInfo": true,
    "generatorVersion": "1.19.0",
    "template": "Basic V2",
    "generatorName": "SAP Fiori Application Generator",
    "entityRelatedConfig": [],
    "launchText": "To launch the generated application, run the following from the generated application root folder:\n\n```\n    npm start\n```"
  }
}
